napalm_oneaccess_oneos/__init__.py
napalm_oneaccess_oneos/oneaccess_oneos.py
napalm_oneaccess_oneos/utils/__init__.py
napalm_oneaccess_oneos-0.1.3.dist-info/AUTHORS
napalm_oneaccess_oneos-0.1.3.dist-info/LICENSE
napalm_oneaccess_oneos-0.1.3.dist-info/METADATA
napalm_oneaccess_oneos-0.1.3.dist-info/WHEEL
napalm_oneaccess_oneos-0.1.3.dist-info/top_level.txt
napalm_oneaccess_oneos-0.1.3.dist-info/RECORD
